Metadata-Version: 2.1
Name: mytask
Version: 0.1.2
Summary: mytask manager tool
Home-page: https://github.com/kasul092/todo
Author: Sumit Pujari
Author-email: sumitpujari199723@gmail.com
License: UNKNOWN
Platform: UNKNOWN
Requires-Python: >=3.6
